copytext.py
copytext-0.2.1.dist-info/METADATA
copytext-0.2.1.dist-info/RECORD
copytext-0.2.1.dist-info/WHEEL
copytext-0.2.1.dist-info/top_level.txt
