Metadata-Version: 2.1
Name: copytext
Version: 0.2.1
Summary: A library for accessing a spreadsheet as a native Python object suitable for templating.
Home-page: http://copytext.readthedocs.org/
Author: NPR Visuals Team
Author-email: nprapps@npr.org
License: MIT
Platform: UNKNOWN
Classifier: Development Status :: 5 - Production/Stable
Classifier: Intended Audience :: Developers
Classifier: License :: OSI Approved :: MIT License
Classifier: Natural Language :: English
Classifier: Operating System :: OS Independent
Classifier: Programming Language :: Python
Classifier: Programming Language :: Python :: 2.7
Classifier: Programming Language :: Python :: 3.3
Classifier: Programming Language :: Python :: 3.4
Classifier: Programming Language :: Python :: 3.5
Classifier: Programming Language :: Python :: 3.6
Classifier: Topic :: Software Development :: Libraries :: Python Modules
Provides-Extra: dev
Requires-Dist: openpyxl (>=2.1.4)
Requires-Dist: six (>=1.10.0)
Provides-Extra: dev
Requires-Dist: Sphinx (==1.5.6); extra == 'dev'
Requires-Dist: nose (==1.1.2); extra == 'dev'
Requires-Dist: unittest2 (==0.5.1); extra == 'dev'
Requires-Dist: coverage (==3.7.1); extra == 'dev'
Requires-Dist: flake8 (==3.5.0); extra == 'dev'
Requires-Dist: tox (==3.0.0); extra == 'dev'
